gree_air_purifier/client.py
gree_air_purifier/const.py
gree_air_purifier/device.py
gree_air_purifier/discovery.py
gree_air_purifier-0.0.6.dist-info/LICENSE
gree_air_purifier-0.0.6.dist-info/METADATA
gree_air_purifier-0.0.6.dist-info/WHEEL
gree_air_purifier-0.0.6.dist-info/top_level.txt
gree_air_purifier-0.0.6.dist-info/RECORD
